reinvent_chemistry/__init__.py
reinvent_chemistry/conversions.py
reinvent_chemistry/descriptors.py
reinvent_chemistry/file_reader.py
reinvent_chemistry/logging.py
reinvent_chemistry/molecular_transformations.py
reinvent_chemistry/phys_chem_descriptors.py
reinvent_chemistry/similarity.py
reinvent_chemistry/tokens.py
reinvent_chemistry/utils.py
reinvent_chemistry/enums/__init__.py
reinvent_chemistry/enums/component_specific_parameters_enum.py
reinvent_chemistry/enums/descriptor_types_enum.py
reinvent_chemistry/enums/filter_types_enum.py
reinvent_chemistry/library_design/__init__.py
reinvent_chemistry/library_design/attachment_points.py
reinvent_chemistry/library_design/bond_maker.py
reinvent_chemistry/library_design/bond_mapper.py
reinvent_chemistry/library_design/failing_reactions_enumerator.py
reinvent_chemistry/library_design/fragment_filter.py
reinvent_chemistry/library_design/fragment_reaction_slice_enumerator.py
reinvent_chemistry/library_design/fragment_reactions.py
reinvent_chemistry/library_design/fragmented_molecule.py
reinvent_chemistry/library_design/aizynth/__init__.py
reinvent_chemistry/library_design/aizynth/aizynth_client.py
reinvent_chemistry/library_design/aizynth/collection_of_pathways_dto.py
reinvent_chemistry/library_design/aizynth/synthetic_pathway_dto.py
reinvent_chemistry/library_design/dtos/__init__.py
reinvent_chemistry/library_design/dtos/failed_reaction_dto.py
reinvent_chemistry/library_design/dtos/filtering_condition_dto.py
reinvent_chemistry/library_design/dtos/reaction_dto.py
reinvent_chemistry/library_design/dtos/reaction_outcome_dto.py
reinvent_chemistry/library_design/dtos/slicing_conditions_dto.py
reinvent_chemistry/library_design/enums/__init__.py
reinvent_chemistry/library_design/enums/molecular_descriptors_enum.py
reinvent_chemistry/library_design/enums/scaffold_memory_fields.py
reinvent_chemistry/library_design/enums/slice_type_enum.py
reinvent_chemistry/library_design/reaction_definitions/__init__.py
reinvent_chemistry-0.0.51.dist-info/LICENSE
reinvent_chemistry-0.0.51.dist-info/METADATA
reinvent_chemistry-0.0.51.dist-info/WHEEL
reinvent_chemistry-0.0.51.dist-info/top_level.txt
reinvent_chemistry-0.0.51.dist-info/RECORD
