Metadata-Version: 2.1
Name: reinvent-chemistry
Version: 0.0.51
Summary: Chemistry functions for Reinvent
Home-page: https://github.com/MolecularAI/reinvent-chemistry
Author: MolecularAI
Author-email: patronov@gmail.com
License: UNKNOWN
Platform: UNKNOWN
Classifier: Programming Language :: Python :: 3
Classifier: License :: OSI Approved :: MIT License
Classifier: Operating System :: OS Independent
Requires-Python: >=3.7
